docs/__init__.py
fagi/__init__.py
fagi/bounded_executor.py
fagi/client.py
fagi/examples/__init__.py
fagi/utils/__init__.py
fagi/utils/constants.py
fagi/utils/errors.py
fagi/utils/logging.py
fagi/utils/types.py
fagi/utils/utils.py
fagi_tcs-0.1.1.dist-info/LICENSE.md
fagi_tcs-0.1.1.dist-info/METADATA
fagi_tcs-0.1.1.dist-info/WHEEL
fagi_tcs-0.1.1.dist-info/top_level.txt
fagi_tcs-0.1.1.dist-info/RECORD
